ScapyZhongwenWendang/README.md
ScapyZhongwenWendang/__init__.py
ScapyZhongwenWendang/__main__.py
ScapyZhongwenWendang/file.epub
ScapyZhongwenWendang/index.html
ScapyZhongwenWendang/css/__init__.py
ScapyZhongwenWendang/css/annotations.css
ScapyZhongwenWendang/css/main.css
ScapyZhongwenWendang/css/normalize.css
ScapyZhongwenWendang/css/popup.css
ScapyZhongwenWendang/font/__init__.py
ScapyZhongwenWendang/font/fontello.eot
ScapyZhongwenWendang/font/fontello.svg
ScapyZhongwenWendang/font/fontello.ttf
ScapyZhongwenWendang/font/fontello.woff
ScapyZhongwenWendang/img/__init__.py
ScapyZhongwenWendang/img/annotator-glyph-sprite.png
ScapyZhongwenWendang/img/annotator-icon-sprite.png
ScapyZhongwenWendang/img/apple-touch-icon.png
ScapyZhongwenWendang/img/cancelfullscreen.png
ScapyZhongwenWendang/img/close.png
ScapyZhongwenWendang/img/fullscreen.png
ScapyZhongwenWendang/img/loader.gif
ScapyZhongwenWendang/img/menu-icon.png
ScapyZhongwenWendang/img/save.png
ScapyZhongwenWendang/img/saved.png
ScapyZhongwenWendang/img/settings-s.png
ScapyZhongwenWendang/img/settings.png
ScapyZhongwenWendang/img/star.png
ScapyZhongwenWendang/js/__init__.py
ScapyZhongwenWendang/js/epub.js
ScapyZhongwenWendang/js/epub.min.js
ScapyZhongwenWendang/js/epub.min.map
ScapyZhongwenWendang/js/hooks.min.js
ScapyZhongwenWendang/js/hooks.min.map
ScapyZhongwenWendang/js/reader.js
ScapyZhongwenWendang/js/reader.js.map
ScapyZhongwenWendang/js/reader.min.js
ScapyZhongwenWendang/js/reader.min.map
ScapyZhongwenWendang/js/hooks/__init__.py
ScapyZhongwenWendang/js/hooks/extensions/__init__.py
ScapyZhongwenWendang/js/hooks/extensions/highlight.js
ScapyZhongwenWendang/js/libs/__init__.py
ScapyZhongwenWendang/js/libs/jquery.min.js
ScapyZhongwenWendang/js/libs/localforage.min.js
ScapyZhongwenWendang/js/libs/screenfull.js
ScapyZhongwenWendang/js/libs/screenfull.min.js
ScapyZhongwenWendang/js/libs/zip.min.js
ScapyZhongwenWendang/js/plugins/__init__.py
ScapyZhongwenWendang/js/plugins/hypothesis.js
scapy_zhongwen_wendang-2024.3.2.0.dist-info/METADATA
scapy_zhongwen_wendang-2024.3.2.0.dist-info/WHEEL
scapy_zhongwen_wendang-2024.3.2.0.dist-info/entry_points.txt
scapy_zhongwen_wendang-2024.3.2.0.dist-info/top_level.txt
scapy_zhongwen_wendang-2024.3.2.0.dist-info/RECORD
